MANIFEST.in
README.rst
setup.py
formica/__init__.py
formica/models.py
formica/version.py
formica.egg-info/PKG-INFO
formica.egg-info/SOURCES.txt
formica.egg-info/dependency_links.txt
formica.egg-info/not-zip-safe
formica.egg-info/requires.txt
formica.egg-info/top_level.txt
formica/templates/formica/base_form.html
formica/templates/formica/table_form.html
formica/templates/formica/bootstrap/base_form.html
formica/templatetags/__init__.py
formica/templatetags/formica.py